<?xml version="1.0" encoding="UTF-8"?>
<!DOCTYPE mapper PUBLIC "-//mybatis.org//DTD Mapper 3.0//EN" "http://mybatis.org/dtd/mybatis-3-mapper.dtd">
<mapper namespace="com.roughindustries.air.client.AirportsMapper">
  <resultMap id="BaseResultMap" type="com.roughindustries.air.model.Airports">
    <!--
      WARNING - @mbggenerated
      This element is automatically generated by MyBatis Generator, do not modify.
      This element was generated on Fri Mar 25 13:56:54 CDT 2016.
    -->
    <result column="iata_code" jdbcType="VARCHAR" property="iataCode" />
    <result column="icao_code" jdbcType="VARCHAR" property="icaoCode" />
    <result column="faa_lid" jdbcType="VARCHAR" property="faaLid" />
    <result column="name" jdbcType="VARCHAR" property="name" />
    <result column="wiki_url" jdbcType="VARCHAR" property="wikiUrl" />
    <result column="wiki_location_served" jdbcType="VARCHAR" property="wikiLocationServed" />
    <result column="wiki_location_server_url" jdbcType="VARCHAR" property="wikiLocationServerUrl" />
    <result column="latitude" jdbcType="DOUBLE" property="latitude" />
    <result column="longitude" jdbcType="DOUBLE" property="longitude" />
  </resultMap>
  <sql id="Example_Where_Clause">
    <!--
      WARNING - @mbggenerated
      This element is automatically generated by MyBatis Generator, do not modify.
      This element was generated on Fri Mar 25 13:56:54 CDT 2016.
    -->
    <where>
      <foreach collection="oredCriteria" item="criteria" separator="or">
        <if test="criteria.valid">
          <trim prefix="(" prefixOverrides="and" suffix=")">
            <foreach collection="criteria.criteria" item="criterion">
              <choose>
                <when test="criterion.noValue">
                  and ${criterion.condition}
                </when>
                <when test="criterion.singleValue">
                  and ${criterion.condition} #{criterion.value}
                </when>
                <when test="criterion.betweenValue">
                  and ${criterion.condition} #{criterion.value} and #{criterion.secondValue}
                </when>
                <when test="criterion.listValue">
                  and ${criterion.condition}
                  <foreach close=")" collection="criterion.value" item="listItem" open="(" separator=",">
                    #{listItem}
                  </foreach>
                </when>
              </choose>
            </foreach>
          </trim>
        </if>
      </foreach>
    </where>
  </sql>
  <sql id="Update_By_Example_Where_Clause">
    <!--
      WARNING - @mbggenerated
      This element is automatically generated by MyBatis Generator, do not modify.
      This element was generated on Fri Mar 25 13:56:54 CDT 2016.
    -->
    <where>
      <foreach collection="example.oredCriteria" item="criteria" separator="or">
        <if test="criteria.valid">
          <trim prefix="(" prefixOverrides="and" suffix=")">
            <foreach collection="criteria.criteria" item="criterion">
              <choose>
                <when test="criterion.noValue">
                  and ${criterion.condition}
                </when>
                <when test="criterion.singleValue">
                  and ${criterion.condition} #{criterion.value}
                </when>
                <when test="criterion.betweenValue">
                  and ${criterion.condition} #{criterion.value} and #{criterion.secondValue}
                </when>
                <when test="criterion.listValue">
                  and ${criterion.condition}
                  <foreach close=")" collection="criterion.value" item="listItem" open="(" separator=",">
                    #{listItem}
                  </foreach>
                </when>
              </choose>
            </foreach>
          </trim>
        </if>
      </foreach>
    </where>
  </sql>
  <sql id="Base_Column_List">
    <!--
      WARNING - @mbggenerated
      This element is automatically generated by MyBatis Generator, do not modify.
      This element was generated on Fri Mar 25 13:56:54 CDT 2016.
    -->
    iata_code, icao_code, faa_lid, name, wiki_url, wiki_location_served, wiki_location_server_url, 
    latitude, longitude
  </sql>
  <select id="selectByExample" parameterType="com.roughindustries.air.model.AirportsExample" resultMap="BaseResultMap">
    <!--
      WARNING - @mbggenerated
      This element is automatically generated by MyBatis Generator, do not modify.
      This element was generated on Fri Mar 25 13:56:54 CDT 2016.
    -->
    select
    <if test="distinct">
      distinct
    </if>
    <include refid="Base_Column_List" />
    from public.airports
    <if test="_parameter != null">
      <include refid="Example_Where_Clause" />
    </if>
    <if test="orderByClause != null">
      order by ${orderByClause}
    </if>
  </select>
  <delete id="deleteByExample" parameterType="com.roughindustries.air.model.AirportsExample">
    <!--
      WARNING - @mbggenerated
      This element is automatically generated by MyBatis Generator, do not modify.
      This element was generated on Fri Mar 25 13:56:54 CDT 2016.
    -->
    delete from public.airports
    <if test="_parameter != null">
      <include refid="Example_Where_Clause" />
    </if>
  </delete>
  <insert id="insert" parameterType="com.roughindustries.air.model.Airports">
    <!--
      WARNING - @mbggenerated
      This element is automatically generated by MyBatis Generator, do not modify.
      This element was generated on Fri Mar 25 13:56:54 CDT 2016.
    -->
    insert into public.airports (iata_code, icao_code, faa_lid, 
      name, wiki_url, wiki_location_served, 
      wiki_location_server_url, latitude, longitude
      )
    values (#{iataCode,jdbcType=VARCHAR}, #{icaoCode,jdbcType=VARCHAR}, #{faaLid,jdbcType=VARCHAR}, 
      #{name,jdbcType=VARCHAR}, #{wikiUrl,jdbcType=VARCHAR}, #{wikiLocationServed,jdbcType=VARCHAR}, 
      #{wikiLocationServerUrl,jdbcType=VARCHAR}, #{latitude,jdbcType=DOUBLE}, #{longitude,jdbcType=DOUBLE}
      )
  </insert>
  <insert id="insertSelective" parameterType="com.roughindustries.air.model.Airports">
    <!--
      WARNING - @mbggenerated
      This element is automatically generated by MyBatis Generator, do not modify.
      This element was generated on Fri Mar 25 13:56:54 CDT 2016.
    -->
    insert into public.airports
    <trim prefix="(" suffix=")" suffixOverrides=",">
      <if test="iataCode != null">
        iata_code,
      </if>
      <if test="icaoCode != null">
        icao_code,
      </if>
      <if test="faaLid != null">
        faa_lid,
      </if>
      <if test="name != null">
        name,
      </if>
      <if test="wikiUrl != null">
        wiki_url,
      </if>
      <if test="wikiLocationServed != null">
        wiki_location_served,
      </if>
      <if test="wikiLocationServerUrl != null">
        wiki_location_server_url,
      </if>
      <if test="latitude != null">
        latitude,
      </if>
      <if test="longitude != null">
        longitude,
      </if>
    </trim>
    <trim prefix="values (" suffix=")" suffixOverrides=",">
      <if test="iataCode != null">
        #{iataCode,jdbcType=VARCHAR},
      </if>
      <if test="icaoCode != null">
        #{icaoCode,jdbcType=VARCHAR},
      </if>
      <if test="faaLid != null">
        #{faaLid,jdbcType=VARCHAR},
      </if>
      <if test="name != null">
        #{name,jdbcType=VARCHAR},
      </if>
      <if test="wikiUrl != null">
        #{wikiUrl,jdbcType=VARCHAR},
      </if>
      <if test="wikiLocationServed != null">
        #{wikiLocationServed,jdbcType=VARCHAR},
      </if>
      <if test="wikiLocationServerUrl != null">
        #{wikiLocationServerUrl,jdbcType=VARCHAR},
      </if>
      <if test="latitude != null">
        #{latitude,jdbcType=DOUBLE},
      </if>
      <if test="longitude != null">
        #{longitude,jdbcType=DOUBLE},
      </if>
    </trim>
  </insert>
  <select id="countByExample" parameterType="com.roughindustries.air.model.AirportsExample" resultType="java.lang.Integer">
    <!--
      WARNING - @mbggenerated
      This element is automatically generated by MyBatis Generator, do not modify.
      This element was generated on Fri Mar 25 13:56:54 CDT 2016.
    -->
    select count(*) from public.airports
    <if test="_parameter != null">
      <include refid="Example_Where_Clause" />
    </if>
  </select>
  <update id="updateByExampleSelective" parameterType="map">
    <!--
      WARNING - @mbggenerated
      This element is automatically generated by MyBatis Generator, do not modify.
      This element was generated on Fri Mar 25 13:56:54 CDT 2016.
    -->
    update public.airports
    <set>
      <if test="record.iataCode != null">
        iata_code = #{record.iataCode,jdbcType=VARCHAR},
      </if>
      <if test="record.icaoCode != null">
        icao_code = #{record.icaoCode,jdbcType=VARCHAR},
      </if>
      <if test="record.faaLid != null">
        faa_lid = #{record.faaLid,jdbcType=VARCHAR},
      </if>
      <if test="record.name != null">
        name = #{record.name,jdbcType=VARCHAR},
      </if>
      <if test="record.wikiUrl != null">
        wiki_url = #{record.wikiUrl,jdbcType=VARCHAR},
      </if>
      <if test="record.wikiLocationServed != null">
        wiki_location_served = #{record.wikiLocationServed,jdbcType=VARCHAR},
      </if>
      <if test="record.wikiLocationServerUrl != null">
        wiki_location_server_url = #{record.wikiLocationServerUrl,jdbcType=VARCHAR},
      </if>
      <if test="record.latitude != null">
        latitude = #{record.latitude,jdbcType=DOUBLE},
      </if>
      <if test="record.longitude != null">
        longitude = #{record.longitude,jdbcType=DOUBLE},
      </if>
    </set>
    <if test="_parameter != null">
      <include refid="Update_By_Example_Where_Clause" />
    </if>
  </update>
  <update id="updateByExample" parameterType="map">
    <!--
      WARNING - @mbggenerated
      This element is automatically generated by MyBatis Generator, do not modify.
      This element was generated on Fri Mar 25 13:56:54 CDT 2016.
    -->
    update public.airports
    set iata_code = #{record.iataCode,jdbcType=VARCHAR},
      icao_code = #{record.icaoCode,jdbcType=VARCHAR},
      faa_lid = #{record.faaLid,jdbcType=VARCHAR},
      name = #{record.name,jdbcType=VARCHAR},
      wiki_url = #{record.wikiUrl,jdbcType=VARCHAR},
      wiki_location_served = #{record.wikiLocationServed,jdbcType=VARCHAR},
      wiki_location_server_url = #{record.wikiLocationServerUrl,jdbcType=VARCHAR},
      latitude = #{record.latitude,jdbcType=DOUBLE},
      longitude = #{record.longitude,jdbcType=DOUBLE}
    <if test="_parameter != null">
      <include refid="Update_By_Example_Where_Clause" />
    </if>
  </update>
</mapper>